yasdu/__init__.py
yasdu/__main__.py
yasdu/frame.py
yasdu/hook.py
yasdu/io.py
yasdu/shell.py
yasdu-1.0.0.dist-info/LICENSE
yasdu-1.0.0.dist-info/METADATA
yasdu-1.0.0.dist-info/WHEEL
yasdu-1.0.0.dist-info/entry_points.txt
yasdu-1.0.0.dist-info/top_level.txt
yasdu-1.0.0.dist-info/RECORD
