Metadata-Version: 2.1
Name: yasdu
Version: 1.0.0
Summary: Yet another stack/session dumper utility
Home-page: https://github.com/mm2pl/yasdu
Author: Mm2PL
Author-email: mm2pl+yasdu@o2.pl
License: UNKNOWN
Platform: UNKNOWN
Classifier: Programming Language :: Python :: 3
Classifier: License :: OSI Approved :: MIT License
Classifier: Operating System :: OS Independent
Classifier: Development Status :: 4 - Beta
Classifier: Environment :: Console
Classifier: Intended Audience :: Developers
Classifier: Topic :: Software Development :: Debuggers
Classifier: Topic :: Software Development :: Libraries :: Python Modules
Classifier: Topic :: Utilities
Requires-Python: >=3.6
